__init__.py
termoweb.py
termoweb-0.1.3.dist-info/licenses/LICENSE
termoweb-0.1.3.dist-info/METADATA
termoweb-0.1.3.dist-info/WHEEL
termoweb-0.1.3.dist-info/top_level.txt
termoweb-0.1.3.dist-info/RECORD
