Metadata-Version: 2.4
Name: termoweb
Version: 0.1.3
Summary: Python client library for controlling Termo thermostats via web interface
Author-email: Dan Faudemer <dan.faudemer@gmail.com>
License: MIT
Project-URL: Homepage, https://github.com/dan/termoweb
Project-URL: Repository, https://github.com/dan/termoweb
Project-URL: Issues, https://github.com/dan/termoweb/issues
Keywords: thermostat,termo,home-automation,temperature-control
Classifier: License :: OSI Approved :: MIT License
Classifier: Programming Language :: Python :: 3
Classifier: Programming Language :: Python :: 3.8
Classifier: Programming Language :: Python :: 3.9
Classifier: Programming Language :: Python :: 3.10
Classifier: Programming Language :: Python :: 3.11
Classifier: Programming Language :: Python :: 3.12
Classifier: Topic :: Home Automation
Requires-Python: >=3.9
License-File: LICENSE
Requires-Dist: httpx>=0.28.1
Dynamic: license-file
